papersai/__init__.py
papersai/index.py
papersai/utils.py
papersai/cli/__init__.py
papersai/cli/daily_papers.py
papersai/cli/qna.py
papersai/cli/summarize.py
papersai/cli/utils.py
papersai/engine/__init__.py
papersai/engine/summarize.py
papersai-0.0.1.dist-info/entry_points.txt
papersai-0.0.1.dist-info/WHEEL
papersai-0.0.1.dist-info/METADATA
papersai-0.0.1.dist-info/RECORD
