Metadata-Version: 2.1
Name: papersai
Version: 0.0.1
Summary: reason about papers using LLMs
Author-email: Saurav Maheshkar <sauravvmaheshkar@gmail.com>
Requires-Python: >=3.8
Classifier: Development Status :: 5 - Production/Stable
Classifier: License :: OSI Approved :: MIT License
Classifier: Programming Language :: Python
Classifier: Programming Language :: Python :: 3.8
Classifier: Programming Language :: Python :: 3.9
Classifier: Programming Language :: Python :: 3.10
Classifier: Programming Language :: Python :: 3.11
Classifier: Programming Language :: Python :: 3 :: Only
Requires-Dist: llama-index
Requires-Dist: llama-index-embeddings-huggingface
Requires-Dist: llama-index-llms-anthropic
Requires-Dist: nltk==3.9b1
Requires-Dist: python-dotenv
Requires-Dist: requests
Requires-Dist: rich
Requires-Dist: build ; extra == "build"
Requires-Dist: twine ; extra == "build"
Requires-Dist: black ; extra == "dev"
Requires-Dist: isort ; extra == "dev"
Requires-Dist: mypy>=0.900 ; extra == "dev"
Requires-Dist: pre-commit>=2.18.0 ; extra == "dev"
Requires-Dist: pytest ; extra == "dev"
Requires-Dist: ruff ; extra == "dev"
Requires-Dist: llama-index-llms-huggingface ; extra == "hf"
Provides-Extra: build
Provides-Extra: dev
Provides-Extra: hf
